bytedturing_inference/__init__.py
bytedturing_inference-0.0.1.dist-info/METADATA
bytedturing_inference-0.0.1.dist-info/WHEEL
bytedturing_inference-0.0.1.dist-info/top_level.txt
bytedturing_inference-0.0.1.dist-info/RECORD
